docassemble.InterviewStats-0.5.0-py3.9-nspkg.pth
docassemble/InterviewStats/__init__.py
docassemble/InterviewStats/cache_geography.py
docassemble/InterviewStats/data_report.py
docassemble/InterviewStats/generate_test_data.py
docassemble/InterviewStats/snapshot_geography.py
docassemble/InterviewStats/snapshot_statistics.py
docassemble/InterviewStats/data/questions/data_report.yml
docassemble/InterviewStats/data/questions/stats.yml
docassemble/InterviewStats/data/questions/subscribe.yml
docassemble/InterviewStats/data/questions/test_create_snapshot_data.yml
docassemble/InterviewStats/data/questions/test_survey_data_generator.yml
docassemble/InterviewStats/data/sources/README.md
docassemble/InterviewStats/data/static/README.md
docassemble/InterviewStats/data/static/styles.css
docassemble/InterviewStats/data/templates/README.md
docassemble.InterviewStats-0.5.0.dist-info/LICENSE
docassemble.InterviewStats-0.5.0.dist-info/METADATA
docassemble.InterviewStats-0.5.0.dist-info/WHEEL
docassemble.InterviewStats-0.5.0.dist-info/namespace_packages.txt
docassemble.InterviewStats-0.5.0.dist-info/top_level.txt
docassemble.InterviewStats-0.5.0.dist-info/RECORD
