Metadata-Version: 2.1
Name: docassemble.InterviewStats
Version: 0.5.0
Summary: A docassemble extension, to view stats from other interviews
Home-page: https://courtformsonline.org/about/
Author: Bryce Willey, Quinten Steenhuis
Author-email: bwilley@suffolk.com
License: The MIT License (MIT)
License-File: LICENSE
Requires-Dist: bokeh (>=2.4.2)
Requires-Dist: cenpy (>=1.0.0.post4)
Requires-Dist: geopandas (>=0.1.0.dev-120828c)
Requires-Dist: numpy (>=1.0.4)
Requires-Dist: pandas (>=1.4.2)
Requires-Dist: requests (>=2.27.1)
